{
	"$schema": "https://schema.management.azure.com/schemas/2015-01-01/deploymentParameters.json#",
	"contentVersion": "1.0.0.0",
	"parameters": {
		"credUserName": "andrey_murzich1",
		"credPassword": "andrey_userpass",
		"runbookLogVerbose": true,
		"runbookLogProgress": true,
		"runbookType": "PowerShellWorkflow",
		"runbookInEdit": false,
		"runbookURI": "[concat(parameters('storagePath'), '/learning4-stopVM.graphrunbook', parameters('sasToken')]",
		"subscriptionId": "Бесплатная пробная версия"
	}
}